inflation/InflationProblem.py
inflation/__init__.py
inflation/_about.py
inflation/_version.py
inflation/optimization_utils.py
inflation/symmetry_utils.py
inflation/utils.py
inflation/lp/InflationLP.py
inflation/lp/__init__.py
inflation/lp/lp_utils.py
inflation/lp/monomial_classes.py
inflation/lp/numbafied.py
inflation/lp/writer_utils.py
inflation/sdp/InflationSDP.py
inflation/sdp/__init__.py
inflation/sdp/fast_npa.py
inflation/sdp/monomial_classes.py
inflation/sdp/monomial_utils.py
inflation/sdp/quantum_tools.py
inflation/sdp/sdp_utils.py
inflation/sdp/writer_utils.py
inflation-2.0.3.dist-info/licenses/LICENSE
inflation-2.0.3.dist-info/METADATA
inflation-2.0.3.dist-info/WHEEL
inflation-2.0.3.dist-info/top_level.txt
inflation-2.0.3.dist-info/RECORD
