Metadata-Version: 2.4
Name: inflation
Version: 2.0.3
Summary: Implementations of the Inflation Technique for Causal Inference
Home-page: https://github.com/ecboghiu/inflation
Author: Emanuel-Cristian Boghiu, Elie Wolfe, Alejandro Pozas-Kerstjens
Author-email: cristian.boghiu@icfo.eu, ewolfe@pitp.ca, physics@alexpozas.com
License: GNU GPL v. 3.0
Project-URL: Documentation, https://ecboghiu.github.io/inflation/_build/html/index.html
Project-URL: Source, https://github.com/ecboghiu/inflation
Project-URL: Issue Tracker, https://github.com/ecboghiu/inflation/issues
Requires-Python: >=3.9
License-File: LICENSE
Requires-Dist: mosek>=10
Requires-Dist: networkx
Requires-Dist: numba
Requires-Dist: numpy
Requires-Dist: scipy>=1.8.0
Requires-Dist: sympy
Requires-Dist: tqdm
Provides-Extra: docs
Requires-Dist: nbsphinx; extra == "docs"
Requires-Dist: m2r2; extra == "docs"
Requires-Dist: sphinx_rtd_theme; extra == "docs"
Requires-Dist: sphinx_copybutton; extra == "docs"
Dynamic: author
Dynamic: author-email
Dynamic: description
Dynamic: description-content-type
Dynamic: home-page
Dynamic: license
Dynamic: license-file
Dynamic: project-url
Dynamic: provides-extra
Dynamic: requires-dist
Dynamic: requires-python
Dynamic: summary
